datasette_pyinstrument/__init__.py
datasette_pyinstrument-0.1.dist-info/METADATA
datasette_pyinstrument-0.1.dist-info/WHEEL
datasette_pyinstrument-0.1.dist-info/entry_points.txt
datasette_pyinstrument-0.1.dist-info/top_level.txt
datasette_pyinstrument-0.1.dist-info/RECORD
