Metadata-Version: 2.1
Name: datasette-pyinstrument
Version: 0.1
Summary: Use pyinstrument to analyze Datasette page performance
Home-page: https://github.com/simonw/datasette-pyinstrument
Author: Simon Willison
License: Apache License, Version 2.0
Project-URL: Issues, https://github.com/simonw/datasette-pyinstrument/issues
Project-URL: CI, https://github.com/simonw/datasette-pyinstrument/actions
Project-URL: Changelog, https://github.com/simonw/datasette-pyinstrument/releases
Platform: UNKNOWN
Requires-Python: >=3.7
Requires-Dist: datasette
Requires-Dist: pyinstrument
Provides-Extra: test
Requires-Dist: pytest ; extra == 'test'
Requires-Dist: pytest-asyncio ; extra == 'test'
